arcade_pylon/__init__.py
arcade_pylon/__main__.py
arcade_pylon/client.py
arcade_pylon/constants.py
arcade_pylon/models/__init__.py
arcade_pylon/models/enums.py
arcade_pylon/models/mappers.py
arcade_pylon/models/api_responses/__init__.py
arcade_pylon/models/api_responses/common.py
arcade_pylon/models/api_responses/contacts.py
arcade_pylon/models/api_responses/issues.py
arcade_pylon/models/api_responses/messages.py
arcade_pylon/models/api_responses/teams.py
arcade_pylon/models/api_responses/user_context.py
arcade_pylon/models/api_responses/users.py
arcade_pylon/models/tool_outputs/__init__.py
arcade_pylon/models/tool_outputs/common.py
arcade_pylon/models/tool_outputs/contacts.py
arcade_pylon/models/tool_outputs/issues.py
arcade_pylon/models/tool_outputs/messages.py
arcade_pylon/models/tool_outputs/search.py
arcade_pylon/models/tool_outputs/teams.py
arcade_pylon/models/tool_outputs/user_context.py
arcade_pylon/models/tool_outputs/users.py
arcade_pylon/tools/__init__.py
arcade_pylon/tools/contacts.py
arcade_pylon/tools/issues.py
arcade_pylon/tools/messages.py
arcade_pylon/tools/teams.py
arcade_pylon/tools/user_context.py
arcade_pylon/tools/users.py
arcade_pylon/utils/__init__.py
arcade_pylon/utils/bm25_utils.py
arcade_pylon/utils/contacts_utils.py
arcade_pylon/utils/date_utils.py
arcade_pylon/utils/fuzzy_utils.py
arcade_pylon/utils/html_utils.py
arcade_pylon/utils/issue_utils.py
arcade_pylon/utils/response_utils.py
arcade_pylon-0.2.0.dist-info/METADATA
arcade_pylon-0.2.0.dist-info/WHEEL
arcade_pylon-0.2.0.dist-info/entry_points.txt
arcade_pylon-0.2.0.dist-info/licenses/LICENSE
arcade_pylon-0.2.0.dist-info/RECORD
