Metadata-Version: 2.4
Name: arcade_pylon
Version: 0.2.0
Summary: Arcade tools designed for LLMs to interact with Pylon
Author-email: Arcade <dev@arcade.dev>
License: Proprietary - Arcade Software License Agreement v1.0
License-File: LICENSE
Requires-Python: >=3.10
Requires-Dist: arcade-mcp-server<2.0.0,>=1.9.2
Requires-Dist: httpx[http2]<0.29.0,>=0.28.0
Requires-Dist: rank-bm25<0.3.0,>=0.2.2
Requires-Dist: rapidfuzz<4.0.0,>=3.11.0
Requires-Dist: typing-extensions<5.0.0,>=4.8.0
Provides-Extra: dev
Requires-Dist: arcade-mcp[evals]<2.0.0,>=1.5.6; extra == 'dev'
Requires-Dist: mypy<1.6.0,>=1.5.1; extra == 'dev'
Requires-Dist: pre-commit<3.5.0,>=3.4.0; extra == 'dev'
Requires-Dist: pytest-asyncio<0.25.0,>=0.24.0; extra == 'dev'
Requires-Dist: pytest-cov<4.1.0,>=4.0.0; extra == 'dev'
Requires-Dist: pytest-mock<3.12.0,>=3.11.1; extra == 'dev'
Requires-Dist: pytest<8.4.0,>=8.3.0; extra == 'dev'
Requires-Dist: ruff<0.8.0,>=0.7.4; extra == 'dev'
Requires-Dist: tox<4.12.0,>=4.11.1; extra == 'dev'
